HealpixMap/__init__.py
HealpixMap/_version.py
HealpixMap/containers/__init__.py
HealpixMap/containers/healpix_base.py
HealpixMap/containers/healpix_map.py
HealpixMap/pixelfunc/__init__.py
HealpixMap/pixelfunc/moc.py
HealpixMap/pixelfunc/single.py
HealpixMap/util/__init__.py
HealpixMap/util/plot.py
HealpixMap-0.1.7.dist-info/LICENSE
HealpixMap-0.1.7.dist-info/METADATA
HealpixMap-0.1.7.dist-info/WHEEL
HealpixMap-0.1.7.dist-info/top_level.txt
HealpixMap-0.1.7.dist-info/RECORD
