Metadata-Version: 2.1
Name: HealpixMap
Version: 0.1.7
Summary: Object-oriented healpy wrapper supporting multi-resolution maps
Home-page: https://gitlab.com/burstcube/HealpixMap
Author: Israel Martinez-Castellanos
Author-email: imc@umd.edu
License: UNKNOWN
Platform: UNKNOWN
Requires-Dist: healpy
